romione/__init__.py
romione/graph/Node.py
romione/graph/__init__.py
romione/graph/compute_utils.py
romione/graph/heuristics.py
romione/graph/node_utils.py
romione/graph/optimize.py
romione/physics/__init__.py
romione/physics/kinematics.yml
romione/physics/physics_kg.py
romione-0.1.2.dist-info/LICENSE
romione-0.1.2.dist-info/METADATA
romione-0.1.2.dist-info/WHEEL
romione-0.1.2.dist-info/top_level.txt
romione-0.1.2.dist-info/RECORD
